cloudflare_bypass/__init__.py
cloudflare_bypass/captcha.py
cloudflare_bypass/cli.py
cloudflare_bypass/config.py
cloudflare_bypass/core.py
cloudflare_bypass/exceptions.py
cloudflare_bypass/utils.py
cloudflare_bypasser-1.0.0.dist-info/licenses/LICENSE
cloudflare_bypasser-1.0.0.dist-info/METADATA
cloudflare_bypasser-1.0.0.dist-info/WHEEL
cloudflare_bypasser-1.0.0.dist-info/entry_points.txt
cloudflare_bypasser-1.0.0.dist-info/top_level.txt
cloudflare_bypasser-1.0.0.dist-info/RECORD
