Metadata-Version: 2.4
Name: cloudflare-bypasser
Version: 1.0.0
Summary: Professional Python library for bypassing Cloudflare protection without external services
Home-page: https://github.com/cloudflarebypass/cloudflare-bypass
Author: CloudflareBypass Team
Author-email: CloudflareBypass Team <dev@cloudflarebypass.com>
Maintainer-email: CloudflareBypass Team <dev@cloudflarebypass.com>
License: MIT
Project-URL: Homepage, https://github.com/cloudflarebypass/cloudflare-bypass
Project-URL: Documentation, https://cloudflarebypass.readthedocs.io/
Project-URL: Repository, https://github.com/cloudflarebypass/cloudflare-bypass.git
Project-URL: Bug Reports, https://github.com/cloudflarebypass/cloudflare-bypass/issues
Project-URL: Changelog, https://github.com/cloudflarebypass/cloudflare-bypass/blob/main/CHANGELOG.md
Keywords: cloudflare,bypass,captcha,selenium,automation,web-scraping,bot-detection,turnstile,challenge
Classifier: Development Status :: 5 - Production/Stable
Classifier: Intended Audience :: Developers
Classifier: License :: OSI Approved :: MIT License
Classifier: Operating System :: OS Independent
Classifier: Programming Language :: Python :: 3
Classifier: Programming Language :: Python :: 3.8
Classifier: Programming Language :: Python :: 3.9
Classifier: Programming Language :: Python :: 3.10
Classifier: Programming Language :: Python :: 3.11
Classifier: Programming Language :: Python :: 3.12
Classifier: Topic :: Internet :: WWW/HTTP :: Browsers
Classifier: Topic :: Software Development :: Libraries :: Python Modules
Classifier: Topic :: System :: Networking
Classifier: Topic :: Utilities
Requires-Python: >=3.8
License-File: LICENSE
Requires-Dist: undetected-chromedriver>=3.5.0
Requires-Dist: selenium>=4.15.0
Requires-Dist: requests>=2.28.0
Provides-Extra: advanced
Requires-Dist: numpy>=1.21.0; extra == "advanced"
Requires-Dist: pillow>=8.0.0; extra == "advanced"
Provides-Extra: ml
Requires-Dist: tensorflow>=2.8.0; extra == "ml"
Requires-Dist: torch>=1.10.0; extra == "ml"
Provides-Extra: dev
Requires-Dist: pytest>=6.0; extra == "dev"
Requires-Dist: pytest-cov>=2.0; extra == "dev"
Requires-Dist: black>=21.0; extra == "dev"
Requires-Dist: flake8>=3.8; extra == "dev"
Requires-Dist: mypy>=0.900; extra == "dev"
Requires-Dist: pre-commit>=2.0; extra == "dev"
Dynamic: author
Dynamic: home-page
Dynamic: license-file
Dynamic: requires-python
